wat/__init__.py
wat_py-0.1.dist-info/METADATA
wat_py-0.1.dist-info/RECORD
wat_py-0.1.dist-info/WHEEL
wat_py-0.1.dist-info/top_level.txt
