Metadata-Version: 2.1
Name: wat-py
Version: 0.1
Summary: Simple interactive breakpoint library with with automatic variable injection.
Home-page: https://github.com/whittlbc/wat-py
Author: Ben Whittle
Author-email: benwhittle31@gmail.com
License: MIT
Platform: UNKNOWN
